{
	"configurations" : 
	[
		{
			"directories" : 
			[
				{
					"build" : ".",
					"hasInstallRule" : true,
					"jsonFile" : "directory-.-Debug-c5b1be7041d5e7f43a47.json",
					"minimumCMakeVersion" : 
					{
						"string" : "3.15"
					},
					"projectIndex" : 0,
					"source" : ".",
					"targetIndexes" : 
					[
						0,
						1,
						2,
						3,
						4,
						5
					]
				}
			],
			"name" : "Debug",
			"projects" : 
			[
				{
					"directoryIndexes" : 
					[
						0
					],
					"name" : "igus_rebel",
					"targetIndexes" : 
					[
						0,
						1,
						2,
						3,
						4,
						5
					]
				}
			],
			"targets" : 
			[
				{
					"directoryIndex" : 0,
					"id" : "igus_moveit::@6890427a1f51a3e7e1df",
					"jsonFile" : "target-igus_moveit-Debug-7d3a4a5e6b23bd4bee24.json",
					"name" : "igus_moveit",
					"projectIndex" : 0
				},
				{
					"directoryIndex" : 0,
					"id" : "igus_rail_moveit::@6890427a1f51a3e7e1df",
					"jsonFile" : "target-igus_rail_moveit-Debug-e4ed877519b7874cc5d0.json",
					"name" : "igus_rail_moveit",
					"projectIndex" : 0
				},
				{
					"directoryIndex" : 0,
					"id" : "igus_rebel::@6890427a1f51a3e7e1df",
					"jsonFile" : "target-igus_rebel-Debug-c0eba12a31cbb4ca661f.json",
					"name" : "igus_rebel",
					"projectIndex" : 0
				},
				{
					"directoryIndex" : 0,
					"id" : "igus_rebel_uninstall::@6890427a1f51a3e7e1df",
					"jsonFile" : "target-igus_rebel_uninstall-Debug-b081f889fc4645a1f2f4.json",
					"name" : "igus_rebel_uninstall",
					"projectIndex" : 0
				},
				{
					"directoryIndex" : 0,
					"id" : "pick_and_place::@6890427a1f51a3e7e1df",
					"jsonFile" : "target-pick_and_place-Debug-b7be57ef46bbf55c98e7.json",
					"name" : "pick_and_place",
					"projectIndex" : 0
				},
				{
					"directoryIndex" : 0,
					"id" : "uninstall::@6890427a1f51a3e7e1df",
					"jsonFile" : "target-uninstall-Debug-c65626e09a3caa2fe992.json",
					"name" : "uninstall",
					"projectIndex" : 0
				}
			]
		}
	],
	"kind" : "codemodel",
	"paths" : 
	{
		"build" : "/home/vasee22/COAR-ROS2-Workspace-mai/COAR-ROS2-Workspace-main/build/igus_rebel",
		"source" : "/home/vasee22/COAR-ROS2-Workspace-mai/COAR-ROS2-Workspace-main/src/igus_rebel_ros2/igus_rebel"
	},
	"version" : 
	{
		"major" : 2,
		"minor" : 6
	}
}
